display_colors/__init__.py
display_colors/__main__.py
display_colors/cell.py
display_colors/cmd/effects.py
display_colors/cmd/eight_bit.py
display_colors/cmd/four_bit.py
display_colors/const.py
display_colors/gen.py
display_colors/init.py
display_colors/math.py
display_colors-1.0.6.dist-info/LICENSE
display_colors-1.0.6.dist-info/METADATA
display_colors-1.0.6.dist-info/WHEEL
display_colors-1.0.6.dist-info/entry_points.txt
display_colors-1.0.6.dist-info/RECORD
