Metadata-Version: 2.1
Name: display-colors
Version: 1.0.6
Summary: Shows the 4-bit color and display effect capabilities of a terminal emulator
Home-page: https://github.com/JoeRodrigue/display-colors
License: Apache-2.0
Keywords: color,terminal,emulator,SGR,ECMA-48
Author: Joe Rodrigue
Author-email: joe.rodrigue@gmail.com
Maintainer: Joe Rodrigue
Maintainer-email: joe.rodrigue@gmail.com
Requires-Python: >=3.7,<4.0
Classifier: License :: OSI Approved :: Apache Software License
Classifier: Operating System :: OS Independent
Classifier: Programming Language :: Python :: 3
Classifier: Programming Language :: Python :: 3.7
Classifier: Programming Language :: Python :: 3.8
Classifier: Programming Language :: Python :: 3.9
Classifier: Programming Language :: Python :: 3.10
Classifier: Programming Language :: Python :: 3.11
Classifier: Programming Language :: Python :: 3.12
Requires-Dist: click (>=8.1.7,<9.0.0)
Project-URL: Documentation, https://github.com/JoeRodrigue/display-colors
Project-URL: Repository, https://github.com/JoeRodrigue/display-colors
